{"cameraMode":{"drawMode":0,"name":"Shaded","section":"Shading Mode"},"sceneLighting":false,"audioPlay":false,"sceneViewState":{"showFog":true,"showMaterialUpdate":false,"showSkybox":false,"showFlares":true,"showImageEffects":true,"showParticleSystems":true},"in2DMode":false,"pivot":{"x":-3.847262382507324,"y":-2.0592200756073,"z":-3.487839698791504},"rotation":{"x":0.14884814620018006,"y":0.10804467648267746,"z":-0.016364669427275659,"w":0.9828087091445923},"size":0.9817808270454407,"orthographic":false}